{
  "chapters": {
    "1": {
      "pendingViews": 4,
      "lastIncrement": "2026-02-16T11:37:53.546Z",
      "lastUpdate": "2026-02-16T00:16:01+07:00"
    },
    "2.1": {
      "pendingViews": 4,
      "lastIncrement": "2026-02-16T11:48:46.819Z",
      "lastUpdate": "2026-02-16T00:16:01+07:00"
    },
    "2.2": {
      "pendingViews": 2,
      "lastIncrement": "2026-02-16T11:50:00.503Z",
      "lastUpdate": "2026-02-16T00:16:01+07:00"
    },
    "2.3": {
      "pendingViews": 2,
      "lastIncrement": "2026-02-16T11:51:19.465Z",
      "lastUpdate": "2026-02-16T00:16:01+07:00"
    },
    "3.1": {
      "pendingViews": 1,
      "lastIncrement": "2026-02-16T10:02:21.553Z",
      "lastUpdate": "2026-02-16T00:16:01+07:00"
    },
    "3.2": {
      "pendingViews": 6,
      "lastIncrement": "2026-02-16T10:02:42.218Z",
      "lastUpdate": "2026-02-16T00:16:01+07:00"
    }
  },
  "lastUpdated": "2026-01-12T21:58:41+07:00"
}