{
  "chapters": {
    "1": {
      "pendingViews": 6,
      "lastIncrement": "2026-02-12T07:23:45.168Z",
      "lastUpdate": "2026-02-12T00:48:19+07:00"
    },
    "2.1": {
      "pendingViews": 2,
      "lastIncrement": "2026-02-12T07:30:55.600Z",
      "lastUpdate": "2026-02-12T00:48:19+07:00"
    },
    "2.2": {
      "pendingViews": 1,
      "lastIncrement": "2026-02-12T07:35:15.897Z",
      "lastUpdate": "2026-02-12T00:48:19+07:00"
    },
    "2.3": {
      "pendingViews": 9,
      "lastIncrement": "2026-02-12T07:39:55.021Z",
      "lastUpdate": "2026-02-12T00:48:19+07:00"
    },
    "3.1": {
      "pendingViews": 20,
      "lastIncrement": "2026-02-12T07:49:46.841Z",
      "lastUpdate": "2026-02-12T00:48:19+07:00"
    },
    "3.2": {
      "pendingViews": 13,
      "lastIncrement": "2026-02-12T07:05:06.341Z",
      "lastUpdate": "2026-02-12T00:48:19+07:00"
    }
  },
  "lastUpdated": "2026-01-12T21:58:41+07:00"
}